{
   "type": "entity",
   "mixins": "stonehearth:mixins:item_properties",
   "components": {
      "render_info": {},
      "model_variants": {
         "default": {
            "layer": "clothing",
            "transparent": false,
            "models": [
               "file(militia_outfit.qb)"
            ]
         },
         "female": {
            "layer": "clothing",
            "transparent": false,
            "models": [
               "file(militia_outfit_female.qb)"
            ]
         }
      },
      "stonehearth:equipment_piece": {
         "render_type": "merge_with_model",
         "slot": "torso"
      }
   },
   "entity_data": {
      "stonehearth:combat:armor_data": {
         "base_damage_reduction": 2
      },
      "stonehearth:catalog": {
         "display_name": "i18n(stonehearth:jobs.militia.militia_outfit.display_name)",
         "description": "i18n(stonehearth:jobs.militia.militia_outfit.description)",
         "icon": "file(militia_outfit.png)"
      }
   }
}
